uscovid_v2.py
uscovid_v2-0.0.1.dist-info/METADATA
uscovid_v2-0.0.1.dist-info/WHEEL
uscovid_v2-0.0.1.dist-info/entry_points.txt
uscovid_v2-0.0.1.dist-info/top_level.txt
uscovid_v2-0.0.1.dist-info/RECORD
