Metadata-Version: 2.1
Name: uscovid-v2
Version: 0.0.1
Summary: covid19 in United States
Home-page: https://github.com/Junya-Toyokura/uscovid_v2
Author: junya toyokura
Author-email: j.toyokura@agreement.jp
License: UNKNOWN
Project-URL: Bug Tracker, https://github.com/Junya-Toyokura/uscovid_v2
Platform: UNKNOWN
Classifier: Programming Language :: Python :: 3
Classifier: License :: OSI Approved :: MIT License
Classifier: Operating System :: OS Independent
Requires-Python: >=3.7
